C3S512/__init__.py
C3S512/cds.py
C3S512-1.0.0.post1.dist-info/LICENSE
C3S512-1.0.0.post1.dist-info/METADATA
C3S512-1.0.0.post1.dist-info/WHEEL
C3S512-1.0.0.post1.dist-info/top_level.txt
C3S512-1.0.0.post1.dist-info/RECORD
