Metadata-Version: 2.1
Name: C3S512
Version: 1.0.0.post1
Summary: Monitor of download activity from the Climate Data Store for quality control
Home-page: UNKNOWN
Author: Jesús Peña-Izquierdo & Iván Cernicharo
Author-email: jesus.pena@bsc.es
License: UNKNOWN
Platform: UNKNOWN
Classifier: Programming Language :: Python :: 3
Classifier: License :: OSI Approved :: MIT License
Classifier: Operating System :: OS Independent
